{
  "time": 1655118808295,
  "blocks": [
    {
      "id": "id_869490",
      "type": "header",
      "data": {
        "text": "Tips on the Best Ways to Protect a Laptop when Bicycle Touring?",
        "level": 1
      },
      "tunes": {
        "AlignmentBlockTune": {
          "alignment": "center"
        }
      }
    },
    {
      "id": "id_48322",
      "type": "paragraph",
      "data": {
        "text": "<i>Hello bike travellers!\n\nFor those who carry laptops with them, I am wondering how you protect them from damage, if you have any tips or tricks? \nI will be taking my Microsoft surface book with me and it has a funny design that doesn't allow it to close flush (refer to photo). I am worried about compressing it too much or warping it when packed in the pannier, on top of the usual worries about laptops. Would love your input!<div class=\"post_attachment\"><div class=\"post_photo_attachment\"><img class=\"post_photo_image\" loading=\"lazy\" src=\"/images/community/tips-on-the-best-ways-to-protect-laptop-when-bicycle-touring/image_1655118638.jpg\" alt=\"\"></div></div></i>"
      },
      "tunes": {
        "AlignmentBlockTune": {
          "alignment": "center"
        }
      }
    },
    {
      "id": "id_394119",
      "type": "delimiter",
      "data": {}
    },
    {
      "id": "id_16500",
      "type": "fbcomment",
      "data": {
        "text": "<div class=\"comment_text\">I would put a layer or two of bubble wrap between the screen and the keys. Then put it into a regular laptop sleeve.</div>",
        "author": "Mark Perry",
        "gender": "UNKNOWN",
        "level": "0"
      },
      "tunes": {
        "AlignmentBlockTune": {
          "alignment": "left"
        }
      }
    },
    {
      "id": "id_5720",
      "type": "fbcomment",
      "data": {
        "text": "<div class=\"comment_text\">Use a hard case. It's bulky but it's the safest option, even during accidents.</div><div class=\"comment_attachment\"><div class=\"comment_photo_attachment\"><img class=\"comment_photo_image\" loading=\"lazy\" src=\"/images/community/tips-on-the-best-ways-to-protect-laptop-when-bicycle-touring/image_1655118640.jpg\" alt=\"\"></div></div>",
        "author": "Bicycle Travellers",
        "gender": "null",
        "level": "0"
      },
      "tunes": {
        "AlignmentBlockTune": {
          "alignment": "left"
        }
      }
    },
    {
      "id": "id_612732",
      "type": "fbcomment",
      "data": {
        "text": "<div class=\"comment_text\">Get a rack pack like the Ortlieb ones and put it in your laptop case inside the rack pack and put your clothes and sleeping bag etc underneath and around it</div>",
        "author": "Menno Pieters",
        "gender": "MALE",
        "level": "0"
      },
      "tunes": {
        "AlignmentBlockTune": {
          "alignment": "left"
        }
      }
    },
    {
      "id": "id_646219",
      "type": "fbcomment",
      "data": {
        "text": "<div class=\"comment_text\">My laptop is between my clothes. 😉</div>",
        "author": "Martin Schweizer",
        "gender": "MALE",
        "level": "0"
      },
      "tunes": {
        "AlignmentBlockTune": {
          "alignment": "left"
        }
      }
    },
    {
      "id": "id_923988",
      "type": "fbcomment",
      "data": {
        "text": "<div class=\"comment_text\">I would use a laptop sleeve for peace of mind. It adds a bit of bulk but will give additional protection from vibration and moisture.</div>",
        "author": "Michael Bryant",
        "gender": "UNKNOWN",
        "level": "0"
      },
      "tunes": {
        "AlignmentBlockTune": {
          "alignment": "left"
        }
      }
    },
    {
      "id": "id_331155",
      "type": "fbcomment",
      "data": {
        "text": "<div class=\"comment_text\">I have a similar laptop and travelled with him from Iceland to Patagonia, nothing bad happens if you carry it inside a special <b>laptop rucksack</b> or bag.. it is made of robust Aluminum... however, the weakest points in these models are: 1) batteries and 2) ventilation, both not good to work with a laptop in warm conditions outdoor, plus, 3) screen reflects everything if you are not indoor... 4) plus, it is rather heavy and expensive to travel with...&nbsp;</div>",
        "author": "Oleg Senkov",
        "gender": "MALE",
        "level": "0"
      },
      "tunes": {
        "AlignmentBlockTune": {
          "alignment": "left"
        }
      }
    },
    {
      "id": "id_463349",
      "type": "fbcomment",
      "data": {
        "text": "<div class=\"comment_text\">I would put a little bubble wrap in between the screen and the keyboard when it’s folded, and also get a laptop sleeve. If you really want some better protection, there are small hard cases you can get for laptops as well.</div>",
        "author": "Tony De Jesus",
        "gender": "MALE",
        "level": "0"
      },
      "tunes": {
        "AlignmentBlockTune": {
          "alignment": "left"
        }
      }
    },
    {
      "id": "id_103572",
      "type": "fbcomment",
      "data": {
        "text": "<div class=\"comment_text\">I carry my electronics (just an iPad mini &amp; accessories) in a locking Eylar hard shell camera case set up as a trunk box bolted to my rear rack with pad eye hooks.  Foam padding inside, waterproof.</div>",
        "author": "Will Taylor",
        "gender": "MALE",
        "level": "0"
      },
      "tunes": {
        "AlignmentBlockTune": {
          "alignment": "left"
        }
      }
    },
    {
      "id": "id_353906",
      "type": "fbcomment",
      "data": {
        "text": "<div class=\"comment_text\">&amp; a 10watt Voltaic Systems solar array mounted atop the case for charging.</div>",
        "author": "Will Taylor",
        "gender": "MALE",
        "level": "1"
      },
      "tunes": {
        "AlignmentBlockTune": {
          "alignment": "left"
        }
      }
    },
    {
      "id": "id_70417",
      "type": "fbcomment",
      "data": {
        "text": "<div class=\"comment_text\">I have a Microsoft surface with me and bought the best-rated case off Amazon.  No issues.</div>",
        "author": "Kim Johnson",
        "gender": "FEMALE",
        "level": "0"
      },
      "tunes": {
        "AlignmentBlockTune": {
          "alignment": "left"
        }
      }
    },
    {
      "id": "id_208480",
      "type": "fbcomment",
      "data": {
        "text": "<div class=\"comment_text\">But a foam rubber sheet with about 1mm in between your laptop to avoid tension (because of the gap) and what I like very much is a 0,5 mm aluminium sheet on both sides of the laptop with an additional 1 mm foam rubber glued on them (on the laptop side). That protects very well, is light and cheap.  You can fix this with a rubber band or in a small bag.</div>",
        "author": "Dieter Ploessl",
        "gender": "MALE",
        "level": "0"
      },
      "tunes": {
        "AlignmentBlockTune": {
          "alignment": "left"
        }
      }
    },
    {
      "id": "id_765916",
      "type": "fbcomment",
      "data": {
        "text": "<div class=\"comment_text\">That will be broken in two weeks.</div>",
        "author": "Javier Colón",
        "gender": "MALE",
        "level": "0"
      },
      "tunes": {
        "AlignmentBlockTune": {
          "alignment": "left"
        }
      }
    },
    {
      "id": "id_887029",
      "type": "fbcomment",
      "data": {
        "text": "<div class=\"comment_text\">If I'm not mistaken, that model is solid-state, ie - no moving parts, robust, and can take a lot of vibration/impact. A guy I met with gazillions of KM's in all conditions kept his really nice camera and pc  in a backpack though. I've hauled that same model a bunch in my rear pannier in a simple waterproof padded case, but in Japan where the roads are smooth as glass for the most part.</div>",
        "author": "Art Rolla",
        "gender": "UNKNOWN",
        "level": "0"
      },
      "tunes": {
        "AlignmentBlockTune": {
          "alignment": "left"
        }
      }
    },
    {
      "id": "id_233201",
      "type": "fbcomment",
      "data": {
        "text": "<div class=\"comment_text\">I do this for almost 20 years. I usually put it vertically in the bag with the closes. There was never a problem with this.</div>",
        "author": "Ulrich Bierwisch",
        "gender": "MALE",
        "level": "0"
      },
      "tunes": {
        "AlignmentBlockTune": {
          "alignment": "left"
        }
      }
    },
    {
      "id": "id_108296",
      "type": "fbcomment",
      "data": {
        "text": "<div class=\"comment_text\">Looks like it needs a shingle in there to prevent over-compression.</div>",
        "author": "Mike Dannheim",
        "gender": "MALE",
        "level": "0"
      },
      "tunes": {
        "AlignmentBlockTune": {
          "alignment": "left"
        }
      }
    }
  ],
  "version": "2.23.2"
}